sthali_backend/__init__.py
sthali_backend/config.py
sthali_backend-0.0.1.dist-info/licenses/LICENSE
sthali_backend-0.0.1.dist-info/METADATA
sthali_backend-0.0.1.dist-info/WHEEL
sthali_backend-0.0.1.dist-info/top_level.txt
sthali_backend-0.0.1.dist-info/RECORD
